{
  "version": "2.0",
  "analysis_type": "GTMØ",
  "timestamp": "2025-09-08T15:32:48.981016",
  "content": {
    "text": "Orzeczenia Trybunału Konstytucyjnego mają moc powszechnie\nobowiązującą i są ostateczne.",
    "length": 87,
    "word_count": 10
  },
  "coordinates": {
    "determination": 0.748467,
    "stability": 0.637714,
    "entropy": 0.394187
  },
  "analysis_metadata": {
    "analyzed_at": "2025-09-08T15:32:48.981016",
    "sequence_number": 0,
    "daily_date": "08092025",
    "sentence_number": 624,
    "saved_at": "2025-09-08T15:32:48.981988",
    "file_counter": 624
  },
  "additional_metrics": {
    "total_analyses": 28,
    "cases": {
      "gen": 5,
      "nom": 7,
      "acc": 6
    },
    "pos": {
      "subst": 7,
      "adj": 8,
      "num": 2,
      "adv": 1,
      "part": 1,
      "conj": 1,
      "interp": 1
    },
    "ambiguity": 2.8,
    "debug_tags": [
      "Orzeczenia:subst:sg:gen:n:ncol",
      "Orzeczenia:subst:pl:nom.acc.voc:n:ncol",
      "Orzeczenia:ger:pl:nom.acc:n:perf:aff",
      "Orzeczenia:ger:sg:gen:n:perf:aff",
      "Trybunału:subst:sg:gen:m3",
      "Konstytucyjnego:adj:sg:acc:m1.m2:pos",
      "Konstytucyjnego:adj:sg:gen:m1.m2.m3.n:pos",
      "mają:fin:pl:ter:imperf",
      "mają:fin:pl:ter:imperf",
      "mają:subst:sg:inst:f"
    ],
    "coords_count": 20
  },
  "interpretation": {
    "determination": "high",
    "stability": "moderate",
    "entropy": "mixed",
    "overall": "moderate_quality",
    "overall_score": 0.6724
  },
  "source_file": "KONSTYTUCJA_RP.md",
  "quantum_metrics": {
    "total_coherence": 0.7109,
    "quantum_words": 7,
    "entanglements": 1,
    "superposition_type": "PARTIALLY_ENTANGLED_MIXED"
  },
  "axiom_protection": {
    "axioms_activated": 0,
    "violations_prevented": 0,
    "meta_reflections": 0
  },
  "quantum_tensor": {
    "value": 0.302632,
    "formula": "0.758 × 0.643 × 0.621 = 0.303"
  },
  "sentence_number": 624,
  "total_sentences": 805
}