{
  "version": "2.0",
  "analysis_type": "GTMØ",
  "timestamp": "2025-09-05T13:39:46.099230",
  "source_file": {
    "path": "C:\\Users\\develop22\\Downloads\\tmø_custom_report.md",
    "name": "tmø_custom_report.md",
    "extension": ".md",
    "hash": "91047b011cf40e816bd9f520899065d51bf6a46cf8b30e06fc1931a1b227acad"
  },
  "content": {
    "text": "[7, 0, 7, 7, 0, 7, 7, 0, 7] [7, 0, 7, 7, 0, 7, 7, 0, 7] [7, 7, 0, 7, 7, 0, 7, 7, 0] [7, 0, 7, 7, 0, 7, 7, 0, 7] [7, 0, 7, 7, 0, 7, 7, 0, 7] [7, 7, 0, 7, 7, 0, 7, 7, 0] [7, 0, 7, 7, 0, 7, 7, 0, 7] [7, 0, 7, 7, 0, 7, 7, 0, 7]",
    "length": 223,
    "word_count": 72
  },
  "coordinates": {
    "determination": 0.8024,
    "stability": 0.968,
    "entropy": 0.032
  },
  "analysis_metadata": {
    "analyzed_at": "2025-09-05T13:39:46.099540",
    "sequence_number": 2507,
    "daily_date": "05092025"
  },
  "interpretation": {
    "determination": "high",
    "stability": "stable",
    "entropy": "ordered",
    "overall": "high_quality",
    "overall_score": 0.9128
  }
}