{
  "version": "2.0",
  "analysis_type": "GTMØ",
  "timestamp": "2025-09-05T13:39:38.646751",
  "source_file": {
    "path": "C:\\Users\\develop22\\Downloads\\GTMØ Topology Core v1 Documentation.md",
    "name": "GTMØ Topology Core v1 Documentation.md",
    "extension": ".md",
    "hash": "c62b72b27fd9e46425b8de9c1ecd1b9c4b9d50ed2807d5ec2b708493cf3e1951"
  },
  "content": {
    "text": "( points=points, showattractors=True, showtrajectories=False ) ```",
    "length": 66,
    "word_count": 6
  },
  "coordinates": {
    "determination": 0.7952,
    "stability": 0.8204,
    "entropy": 0.1868
  },
  "analysis_metadata": {
    "analyzed_at": "2025-09-05T13:39:38.647190",
    "sequence_number": 2166,
    "daily_date": "05092025"
  },
  "interpretation": {
    "determination": "high",
    "stability": "stable",
    "entropy": "ordered",
    "overall": "high_quality",
    "overall_score": 0.8096
  }
}