{
  "version": "2.0",
  "analysis_type": "GTMØ",
  "timestamp": "2025-09-05T13:39:29.228121",
  "source_file": {
    "path": "C:\\Users\\develop22\\Downloads\\gtmo-fractal-docs-en.md",
    "name": "gtmo-fractal-docs-en.md",
    "extension": ".md",
    "hash": "4cb01a59f86bc26e502643ea23e43febce14bcee9c21fdb16ad0f09c793a1119"
  },
  "content": {
    "text": "points = fractal.semantic_ifs( \"language\", transforms, iterations=1000 )",
    "length": 72,
    "word_count": 7
  },
  "coordinates": {
    "determination": 0.7952,
    "stability": 0.8348,
    "entropy": 0.176
  },
  "analysis_metadata": {
    "analyzed_at": "2025-09-05T13:39:29.228556",
    "sequence_number": 1689,
    "daily_date": "05092025"
  },
  "interpretation": {
    "determination": "high",
    "stability": "stable",
    "entropy": "ordered",
    "overall": "high_quality",
    "overall_score": 0.818
  }
}