{
  "version": "2.0",
  "analysis_type": "GTMØ",
  "timestamp": "2025-09-05T13:39:47.100559",
  "source_file": {
    "path": "C:\\Users\\develop22\\Downloads\\topology_v2_optimized_docs.md",
    "name": "topology_v2_optimized_docs.md",
    "extension": ".md",
    "hash": "cceb55353a8333bf983f9a98eb6ad1160e6ed04bd0b88cc18beceb0ac20d4470"
  },
  "content": {
    "text": "system.addoptimizedparticle( content=f\"particle_{i}\", determinacy=np.random.uniform(0.1, 0.9), stability=np.random.uniform(0.1, 0.9), entropy=np.random.uniform(0.1, 0.9) )",
    "length": 171,
    "word_count": 9
  },
  "coordinates": {
    "determination": 0.763615,
    "stability": 0.870262,
    "entropy": 0.186754
  },
  "analysis_metadata": {
    "analyzed_at": "2025-09-05T13:39:47.100862",
    "sequence_number": 2552,
    "daily_date": "05092025"
  },
  "interpretation": {
    "determination": "high",
    "stability": "stable",
    "entropy": "ordered",
    "overall": "high_quality",
    "overall_score": 0.8157
  }
}