{
  "version": "2.0",
  "analysis_type": "GTMØ",
  "timestamp": "2025-09-08T15:32:37.865566",
  "content": {
    "text": "Nikt nie może być obowiązany przez organy władzy publicznej do\nujawnienia swojego światopoglądu, przekonań religijnych lub wyznania.",
    "length": 132,
    "word_count": 17
  },
  "coordinates": {
    "determination": 0.688807,
    "stability": 0.610445,
    "entropy": 0.467953
  },
  "analysis_metadata": {
    "analyzed_at": "2025-09-08T15:32:37.865566",
    "sequence_number": 0,
    "daily_date": "08092025",
    "sentence_number": 150,
    "saved_at": "2025-09-08T15:32:37.865961",
    "file_counter": 150
  },
  "additional_metrics": {
    "total_analyses": 51,
    "cases": {
      "nom": 12,
      "acc": 7,
      "gen": 16,
      "voc": 1,
      "dat": 2,
      "loc": 2
    },
    "pos": {
      "subst": 18,
      "conj": 2,
      "part": 2,
      "adj": 10,
      "prep": 2,
      "interp": 2
    },
    "ambiguity": 3.0,
    "debug_tags": [
      "Nikt:subst:sg:nom:m1",
      "nie:conj",
      "nie:interj",
      "nie:ppron3:pl:acc:m2.m3.f.n:ter:akc.nakc:praep",
      "nie:ppron3:sg:acc:n:ter:akc.nakc:praep",
      "nie:part",
      "może:interj",
      "może:part",
      "może:fin:sg:ter:imperf",
      "być:subst:pl:gen:n:ncol"
    ],
    "coords_count": 38
  },
  "interpretation": {
    "determination": "moderate",
    "stability": "moderate",
    "entropy": "mixed",
    "overall": "moderate_quality",
    "overall_score": 0.6183
  },
  "source_file": "KONSTYTUCJA_RP.md",
  "quantum_metrics": {
    "total_coherence": 0.9451,
    "quantum_words": 15,
    "entanglements": 5,
    "superposition_type": "COHERENT_SUPERPOSITION"
  },
  "axiom_protection": {
    "axioms_activated": 0,
    "violations_prevented": 0,
    "meta_reflections": 0
  },
  "quantum_tensor": {
    "value": 0.235272,
    "formula": "0.699 × 0.615 × 0.547 = 0.235"
  },
  "sentence_number": 150,
  "total_sentences": 805
}