{
  "version": "2.0",
  "analysis_type": "GTMØ",
  "timestamp": "2025-09-05T13:20:52.959627",
  "source_file": {
    "path": "C:\\Users\\develop22\\Downloads\\topology_v2_optimized_docs.md",
    "name": "topology_v2_optimized_docs.md",
    "extension": ".md",
    "hash": "cceb55353a8333bf983f9a98eb6ad1160e6ed04bd0b88cc18beceb0ac20d4470"
  },
  "content": {
    "text": "- : Enhanced GTMØ system with universe modes - : Optimized trajectory observer and epistemic system - : Core knowledge entity definitions",
    "length": 137,
    "word_count": 22
  },
  "coordinates": {
    "determination": 0.71,
    "stability": 0.7356,
    "entropy": 0.3206
  },
  "analysis_metadata": {
    "analyzed_at": "2025-09-05T13:20:52.960009",
    "sequence_number": 603,
    "daily_date": "05092025"
  },
  "additional_metrics": {
    "header": "Required GTMØ Modules",
    "text": "- : Enhanced GTMØ system with universe modes - : Optimized trajectory observer and epistemic system - : Core knowledge entity definitions",
    "char_count": 137,
    "word_count": 22
  },
  "interpretation": {
    "determination": "high",
    "stability": "stable",
    "entropy": "ordered",
    "overall": "high_quality",
    "overall_score": 0.7083
  }
}