{
  "version": "2.0",
  "analysis_type": "GTMØ",
  "timestamp": "2025-09-05T13:39:39.732446",
  "source_file": {
    "path": "C:\\Users\\develop22\\Downloads\\Indefiniteness Core_PL.md",
    "name": "Indefiniteness Core_PL.md",
    "extension": ".md",
    "hash": "40efa8084707c7f44670075167ff3640de614304eee89f947fc20ce4a41b4e90"
  },
  "content": {
    "text": "#",
    "length": 1,
    "word_count": 1
  },
  "coordinates": {
    "determination": 0.5072,
    "stability": 0.5036,
    "entropy": 0.4964
  },
  "analysis_metadata": {
    "analyzed_at": "2025-09-05T13:39:39.732762",
    "sequence_number": 2219,
    "daily_date": "05092025"
  },
  "interpretation": {
    "determination": "medium",
    "stability": "moderate",
    "entropy": "mixed",
    "overall": "moderate_quality",
    "overall_score": 0.5048
  }
}