{
  "version": "2.0",
  "analysis_type": "GTMØ",
  "timestamp": "2025-09-08T15:32:37.278291",
  "content": {
    "text": "Rodzice mają prawo do wychowania dzieci zgodnie z własnymi\nprzekonaniami.",
    "length": 73,
    "word_count": 10
  },
  "coordinates": {
    "determination": 0.773626,
    "stability": 0.637902,
    "entropy": 0.372345
  },
  "analysis_metadata": {
    "analyzed_at": "2025-09-08T15:32:37.278291",
    "sequence_number": 0,
    "daily_date": "08092025",
    "sentence_number": 121,
    "saved_at": "2025-09-08T15:32:37.278572",
    "file_counter": 121
  },
  "additional_metrics": {
    "total_analyses": 27,
    "cases": {
      "nom": 9,
      "gen": 5
    },
    "pos": {
      "subst": 13,
      "adv": 2,
      "prep": 3,
      "part": 1,
      "adj": 1,
      "interp": 1
    },
    "ambiguity": 2.7,
    "debug_tags": [
      "Rodzice:subst:pl:nom.voc:m1:pt",
      "Rodzice:subst:pl:nom.voc:m1",
      "Rodzice:subst:pl:nom.acc.voc:f",
      "Rodzice:depr:pl:nom.acc.voc:m2",
      "mają:fin:pl:ter:imperf",
      "mają:fin:pl:ter:imperf",
      "mają:subst:sg:inst:f",
      "prawo:subst:sg:nom.acc.voc:n:ncol",
      "prawo:adv:pos",
      "do:prep:gen"
    ],
    "coords_count": 21
  },
  "interpretation": {
    "determination": "high",
    "stability": "moderate",
    "entropy": "mixed",
    "overall": "moderate_quality",
    "overall_score": 0.6891
  },
  "source_file": "KONSTYTUCJA_RP.md",
  "quantum_metrics": {
    "total_coherence": 1.1428,
    "quantum_words": 6,
    "entanglements": 2,
    "superposition_type": "COHERENT_SUPERPOSITION"
  },
  "axiom_protection": {
    "axioms_activated": 0,
    "violations_prevented": 0,
    "meta_reflections": 0
  },
  "quantum_tensor": {
    "value": 0.323766,
    "formula": "0.784 × 0.643 × 0.643 = 0.324"
  },
  "sentence_number": 121,
  "total_sentences": 805
}