{
  "version": "2.0",
  "analysis_type": "GTMØ",
  "timestamp": "2025-09-05T13:39:29.118191",
  "source_file": {
    "path": "C:\\Users\\develop22\\Downloads\\gtmo-fractal-docs-en.md",
    "name": "gtmo-fractal-docs-en.md",
    "extension": ".md",
    "hash": "4cb01a59f86bc26e502643ea23e43febce14bcee9c21fdb16ad0f09c793a1119"
  },
  "content": {
    "text": "trajectory = fractal.iterate_meaning( point, fractal.attractors[3], # Ø - Singularity steps=50 )",
    "length": 96,
    "word_count": 11
  },
  "coordinates": {
    "determination": 0.7704,
    "stability": 0.791855,
    "entropy": 0.229418
  },
  "analysis_metadata": {
    "analyzed_at": "2025-09-05T13:39:29.118507",
    "sequence_number": 1682,
    "daily_date": "05092025"
  },
  "interpretation": {
    "determination": "high",
    "stability": "stable",
    "entropy": "ordered",
    "overall": "high_quality",
    "overall_score": 0.7776
  }
}