{
  "version": "2.0",
  "analysis_type": "GTMØ",
  "timestamp": "2025-09-08T13:01:44.535339",
  "content": {
    "text": "Sejm wybiera ze swojego grona Marszałka Sejmu i\nwicemarszałków.",
    "length": 63,
    "word_count": 9
  },
  "coordinates": {
    "determination": 0.678273,
    "stability": 0.574747,
    "entropy": 0.489159
  },
  "analysis_metadata": {
    "analyzed_at": "2025-09-08T13:01:44.535339",
    "sequence_number": 413,
    "daily_date": "08092025"
  },
  "additional_metrics": {
    "total_analyses": 18,
    "cases": {
      "nom": 2,
      "gen": 8,
      "acc": 1
    },
    "pos": {
      "subst": 8,
      "prep": 2,
      "part": 2,
      "adj": 2,
      "conj": 1,
      "interp": 1
    },
    "ambiguity": 2.0,
    "debug_tags": [
      "Sejm:subst:sg:nom.acc:m3",
      "wybiera:fin:sg:ter:imperf",
      "ze:prep:gen:wok",
      "ze:prep:inst:wok",
      "ze:part:wok",
      "swojego:adj:sg:acc:m1.m2:pos",
      "swojego:adj:sg:gen:m1.m2.m3.n:pos",
      "swojego:subst:sg:gen:n:ncol",
      "grona:subst:sg:gen:n:ncol",
      "grona:subst:pl:nom.acc.voc:n:ncol"
    ],
    "coords_count": 19
  },
  "interpretation": {
    "determination": "moderate",
    "stability": "moderate",
    "entropy": "mixed",
    "overall": "moderate_quality",
    "overall_score": 0.597
  },
  "console_like": [
    "  MORPHOLOGY: coords_found=19, cases={'nom': 2, 'gen': 8, 'acc': 1}, pos={'subst': 8, 'prep': 2, 'part': 2, 'adj': 2, 'conj': 1, 'interp': 1}",
    "  MORPH_COORDS: [0.693, 0.621, 0.442]",
    "  MORPH_TAGS: ['Sejm:subst:sg:nom.acc:m3', 'wybiera:fin:sg:ter:imperf', 'ze:prep:gen:wok', 'ze:prep:inst:wok', 'ze:part:wok', 'swojego:adj:sg:acc:m1.m2:pos', 'swojego:adj:sg:gen:m1.m2.m3.n:pos', 'swojego:subst:sg:gen:n:ncol', 'grona:subst:sg:gen:n:ncol', 'grona:subst:pl:nom.acc.voc:n:ncol']",
    "  SYNTAX_COORDS: [0.673, 0.452, 0.572]",
    "  FINAL: D=0.688, S=0.580, E=0.474"
  ],
  "source_file": {
    "path": "C:\\Users\\develop22\\Desktop\\KONSTYTUCJA_RP.md",
    "name": "KONSTYTUCJA_RP.md",
    "extension": ".md",
    "hash": "8291cc49c13bed0b4cc61374ccd96506fb1f16f7e9a93e4a5ee516fda4151987"
  },
  "quantum_metrics": {
    "total_coherence": 1.1443,
    "quantum_words": 7,
    "entanglements": 1,
    "superposition_type": "COHERENT_SUPERPOSITION"
  },
  "axiom_protection": {
    "axioms_activated": 1,
    "violations_prevented": 0,
    "meta_reflections": 0
  }
}